scripts/api_audio_speech_test.py
scripts/openai_audio_speech_test.py
scripts/stress_vibevoice_api.py
scripts/test_vibevoice_api.py
tests/vibevoice_api/test_admin_keys.py
tests/vibevoice_api/test_audio_utils.py
tests/vibevoice_api/test_voice_map.py
vibevoice_api/__init__.py
vibevoice_api/audio_utils.py
vibevoice_api/auth.py
vibevoice_api/config.py
vibevoice_api/observability.py
vibevoice_api/server.py
vibevoice_api/tts_engine.py
vibevoice_api/voice_map.py
vibevoice_api-0.0.1.dist-info/licenses/LICENSE
vibevoice_api-0.0.1.dist-info/METADATA
vibevoice_api-0.0.1.dist-info/WHEEL
vibevoice_api-0.0.1.dist-info/top_level.txt
vibevoice_api-0.0.1.dist-info/RECORD
