Metadata-Version: 2.4
Name: vibevoice-api
Version: 0.0.1
Summary: A model for speech generation with an AR + diffusion architecture.
Author-email: vibevoice team <vibepod@microsoft.com>
Project-URL: Homepage, https://github.com/vibevoice-community/VibeVoice-API
Project-URL: Bug Tracker, https://github.com/vibevoice-community/VibeVoice-API/issues
Classifier: Programming Language :: Python :: 3
Classifier: Operating System :: OS Independent
Requires-Python: >=3.9
License-File: LICENSE
Requires-Dist: torch
Requires-Dist: accelerate==1.6.0
Requires-Dist: transformers==4.51.3
Requires-Dist: datasets==3.5.0
Requires-Dist: peft
Requires-Dist: llvmlite>=0.40.0
Requires-Dist: numba>=0.57.0
Requires-Dist: diffusers
Requires-Dist: tqdm
Requires-Dist: numpy
Requires-Dist: scipy
Requires-Dist: librosa
Requires-Dist: ml-collections
Requires-Dist: absl-py
Requires-Dist: gradio
Requires-Dist: av
Requires-Dist: aiortc
Dynamic: license-file
